pyexams/__init__.py
pyexams/metadata_collector.py
pyexams/pyexams.py
pyexams/send.py
pyexams-0.3.3.data/scripts/pyexams
pyexams-0.3.3.dist-info/LICENSE
pyexams-0.3.3.dist-info/METADATA
pyexams-0.3.3.dist-info/WHEEL
pyexams-0.3.3.dist-info/top_level.txt
pyexams-0.3.3.dist-info/RECORD
