Metadata-Version: 2.1
Name: pyexams
Version: 0.3.3
Summary: Generates variants of exam questions using texsurgery, keeps a question database, exports to pdf and moodle
Home-page: https://framagit.org/pang/pyexams
Author: Pablo Angulo
Author-email: pablo.angulo@upm.es
License: UNKNOWN
Platform: UNKNOWN
Classifier: Programming Language :: Python :: 3
Classifier: License :: OSI Approved :: MIT License
Classifier: Operating System :: OS Independent
Requires-Python: >=3.6
Requires-Dist: texsurgery
Requires-Dist: amc2moodle
Requires-Dist: pydal
Requires-Dist: joblib
Requires-Dist: appdirs
